dnaapler/__init__.py
dnaapler/db/README.md
dnaapler/db/all.faa
dnaapler/db/all_db
dnaapler/db/all_db.dbtype
dnaapler/db/all_db.index
dnaapler/db/all_db.lookup
dnaapler/db/all_db.source
dnaapler/db/all_db_h
dnaapler/db/all_db_h.dbtype
dnaapler/db/all_db_h.index
dnaapler/db/cog1474.fasta
dnaapler/db/cog1474_db
dnaapler/db/cog1474_db.dbtype
dnaapler/db/cog1474_db.index
dnaapler/db/cog1474_db.lookup
dnaapler/db/cog1474_db.source
dnaapler/db/cog1474_db_h
dnaapler/db/cog1474_db_h.dbtype
dnaapler/db/cog1474_db_h.index
dnaapler/db/dnaA.faa
dnaapler/db/dnaA_db
dnaapler/db/dnaA_db.dbtype
dnaapler/db/dnaA_db.index
dnaapler/db/dnaA_db.lookup
dnaapler/db/dnaA_db.source
dnaapler/db/dnaA_db_h
dnaapler/db/dnaA_db_h.dbtype
dnaapler/db/dnaA_db_h.index
dnaapler/db/dnaA_repA.faa
dnaapler/db/dnaA_repA_db
dnaapler/db/dnaA_repA_db.dbtype
dnaapler/db/dnaA_repA_db.index
dnaapler/db/dnaA_repA_db.lookup
dnaapler/db/dnaA_repA_db.source
dnaapler/db/dnaA_repA_db_h
dnaapler/db/dnaA_repA_db_h.dbtype
dnaapler/db/dnaA_repA_db_h.index
dnaapler/db/dnaA_terL.faa
dnaapler/db/dnaA_terL_db
dnaapler/db/dnaA_terL_db.dbtype
dnaapler/db/dnaA_terL_db.index
dnaapler/db/dnaA_terL_db.lookup
dnaapler/db/dnaA_terL_db.source
dnaapler/db/dnaA_terL_db_h
dnaapler/db/dnaA_terL_db_h.dbtype
dnaapler/db/dnaA_terL_db_h.index
dnaapler/db/repA.faa
dnaapler/db/repA_db
dnaapler/db/repA_db.dbtype
dnaapler/db/repA_db.index
dnaapler/db/repA_db.lookup
dnaapler/db/repA_db.source
dnaapler/db/repA_db_h
dnaapler/db/repA_db_h.dbtype
dnaapler/db/repA_db_h.index
dnaapler/db/repA_terL.faa
dnaapler/db/repA_terL_db
dnaapler/db/repA_terL_db.dbtype
dnaapler/db/repA_terL_db.index
dnaapler/db/repA_terL_db.lookup
dnaapler/db/repA_terL_db.source
dnaapler/db/repA_terL_db_h
dnaapler/db/repA_terL_db_h.dbtype
dnaapler/db/repA_terL_db_h.index
dnaapler/db/terL.faa
dnaapler/db/terL_db
dnaapler/db/terL_db.dbtype
dnaapler/db/terL_db.index
dnaapler/db/terL_db.lookup
dnaapler/db/terL_db.source
dnaapler/db/terL_db_h
dnaapler/db/terL_db_h.dbtype
dnaapler-1.3.0.dist-info/AUTHORS.md
dnaapler-1.3.0.dist-info/LICENSE
dnaapler-1.3.0.dist-info/METADATA
dnaapler-1.3.0.dist-info/WHEEL
dnaapler-1.3.0.dist-info/entry_points.txt
dnaapler-1.3.0.dist-info/RECORD
